pda_api_wrapper/__init__.py
pda_api_wrapper/pda_api.py
pda_api_wrapper-1.0.dist-info/LICENSE
pda_api_wrapper-1.0.dist-info/METADATA
pda_api_wrapper-1.0.dist-info/WHEEL
pda_api_wrapper-1.0.dist-info/top_level.txt
pda_api_wrapper-1.0.dist-info/RECORD
